planetool.py
planetool-0.1.dist-info/LICENSE
planetool-0.1.dist-info/METADATA
planetool-0.1.dist-info/WHEEL
planetool-0.1.dist-info/top_level.txt
planetool-0.1.dist-info/RECORD
