Metadata-Version: 2.1
Name: planetool
Version: 0.1
Summary: planetool, manyetik alanlar, gelgit kuvvetleri, ısı akışı ve daha fazlasını içeren gezegen bilim hesaplamaları için tasarlanmış bir Python sınıfıdır. Bu sınıf, manyetik alanlar, Coriolis kuvvetleri, gelgit kuvvetleri, dalga enerjisi, basınç ve Gibbs enerjisi gibi fiziksel fenomenleri tanımlamak için matematiksel modelleri içeren geniş bir gezegen fiziği işlevleri yelpazesi sunar.
Home-page: https://github.com/GizemSena/planetool
Author: Gizem Sena Çengel
Author-email: gizemsenac@gmail.com
License: MIT
Keywords: Exoplanet,physics
Classifier: License :: OSI Approved :: MIT License
Classifier: Programming Language :: Python :: 3.12
License-File: LICENSE
